Control_unit.v
/*************************************************************************/
/****        Author         :   Eslam Hussein                         ****/
/****        Module         :   Control Unit                          ****/
/****        Project Name   :   UART Transmitter                      ****/
/****        Date           :   1 August 2021                         ****/
/****        Version        :   V.01                                  ****/
/*************************************************************************/


/************************ Module Definition  *****************************/ 
module  Control_Unit  

/************************ Module Interface   *****************************/
     (
		 input  wire  [2:0]COUNT ,
         input  wire  CLK ,
		 input  wire  RST ,
		 input  wire  Data_Valid ,
		 output reg   SHIFT,
		 output reg   [1:0]SEL ,
		 output reg   COUNT_EN , 
		 output reg   busy , 		 
		 output reg   Load
     );
	 
/************************  Module Body   *********************************/
/*  States Encoding  */ 
localparam  [2:0] IDLE       = 3'b000 ,
                  START      = 3'b001 ,
                  D_SH       = 3'b011 ,
                  INS_PAR    = 3'b111 ,
                  STOP       = 3'b110 ;
reg         [2:0] Current_State , Next_State ;

/* Next State Transition */ 
always @(posedge CLK or negedge RST)
     begin
	     if(!RST)
	         begin			 
			     Current_State <= IDLE ; 	
			 end	    
	     else 
		     begin
			     Current_State <= Next_State ; 	
			 end 			 
	 end
/* Next State Logic */ 	 
always @(*)
     begin
	     case(Current_State)
		     IDLE : 
			         begin
					     if (Data_Valid==1'b1)
					         begin
					 	  	     Next_State = START ;			 							 
					         end
					     else 
						     begin
							     Next_State = IDLE ;							 							 
							 end					 
					 end
		     START : 
			         begin
						 Next_State = D_SH ;							 							 	
					 end
		     D_SH : 			         
			         begin
					     if (COUNT ==3'b111)
					         begin
					 	  	     Next_State = INS_PAR ;			 							 
					         end
					     else 
						     begin
							     Next_State = D_SH ;							 							 
							 end						 

					 end
		     INS_PAR : 
			         begin
					     Next_State = STOP ;							 					
					 end					 
		     STOP : 
			         begin
						 Next_State = IDLE ;							 							 					 
					 end	
             default :
			 	     begin
						 Next_State = IDLE ;							 							 					 
					 end	
		 endcase
	 end	 
/* Output Logic */
always @(*)
     begin
         SHIFT = 1'b0 ;
         SEL = 2'b00 ;
         COUNT_EN = 1'b0 ;
         busy = 1'b0 ;	 
         Load =  1'b0 ;
	     case(Current_State)
		     IDLE : 
			         begin
					     busy = 1'b0 ;
					     SEL = 2'b00 ;
					 end
		     START : 
			         begin
					     busy = 1'b1 ;	 
                         Load = 1'b1 ;
					 	 SEL  = 2'b01 ;
					 end
		     D_SH : 
			         begin
					     busy = 1'b1 ;	 
                         COUNT_EN = 1'b1 ;
					 	 SEL  = 2'b10 ;					 
                         SHIFT = 1'b1 ;
					 end
		     INS_PAR : 
			         begin
					     busy = 1'b1 ;	 
					 	 SEL  = 2'b11 ; 
					 end					 
		     STOP : 
			         begin
					     busy = 1'b1 ;	 
					 	 SEL  = 2'b00 ; 					 
					 end
             default :
			 	     begin
				         SHIFT = 1'b0 ;
                         SEL = 2'b00 ;
                         COUNT_EN = 1'b0 ;
                         busy = 1'b0 ;	 
                         Load =  1'b0 ;
					 end						 
		 endcase
	 end



/****************************  Module End  ****************************/
endmodule

MUX.v
/*************************************************************************/
/****        Author         :   Eslam Hussein                         ****/
/****        Module         :   Multiplexer                           ****/
/****        Project Name   :   UART Transmitter                      ****/
/****        Date           :   1 August 2021                         ****/
/****        Version        :   V.01                                  ****/
/*************************************************************************/

/************************ Module Definition  *****************************/ 
module MUX  

/************************ Module Interface   *****************************/

     (
         input  wire I_0 ,
         input  wire I_1 ,
         input  wire I_2 ,
         input  wire I_3 ,
		 input  wire [1:0]SEL ,
		 output reg OUT
     );
	 
/************************  Module Body   *********************************/
/* Always Block */ 
always @(*)
     begin
	    case(SEL)
		     2'b00 : 
			         begin
					     OUT = I_0;				 
					 end
		     2'b01 : 
			         begin
					     OUT = I_1;				 					 
					 end		
		     2'b10 : 
			         begin
					     OUT = I_2;				 					 
					 end		
		     2'b11 : 
			         begin
					     OUT = I_3;				 					 
					 end				
		endcase
	 end

/****************************  Module End  ****************************/
endmodule

Parity_Calculator.v
/*************************************************************************/
/****        Author         :   Eslam Hussein                         ****/
/****        Module         :   Parity_Calculator                     ****/
/****        Project Name   :   UART Transmitter                      ****/
/****        data           :   1 August 2021                         ****/
/****        Version        :   V.01                                  ****/
/*************************************************************************/


/************************ Module Definition  *****************************/ 
module Parity_Calculator  

/************************ Module Interface   *****************************/
     (
		 input  wire [7:0]DATA_IN ,
         input  wire  CLK ,
		 input  wire  RST ,
		 input  wire  Load ,
		 output wire  Parity_Bit 
     );
	 
/************************  Module Body   *********************************/
/* Signal Declaration */ 
reg [7:0] data ; 
/* Always Block */ 
always @(posedge CLK or negedge RST)
     begin
	     if(!RST)
	         begin			 
			     data <= 8'b00000000 ; 	
			 end
	     else if (Load)
		     begin
			     
	             data <= DATA_IN ;	       			 
	         end
	     else
		     begin
				 data <= data ;
			 end 
	 end
/* Assign Statement */
assign Parity_Bit = data[7] ^ data[6] ^ data[5] ^ data[4] ^ data[3] ^ data[2] ^ data[1] ^ data[0] ;

/****************************  Module End  ****************************/
endmodule

Counter.v
/*************************************************************************/
/****        Author         :   Eslam Hussein                         ****/
/****        Module         :   Counter                               ****/
/****        Project Name   :   UART Transmitter                      ****/
/****        Date           :   1 August 2021                         ****/
/****        Version        :   V.01                                  ****/
/*************************************************************************/

/************************ Module Definition  *****************************/ 
module Counter  

/************************ Module Interface   *****************************/

     (
         input wire CLK ,
		 input wire RST ,
		 input wire EN ,
		 output reg [2:0]COUNT
     );
	 
/************************  Module Body   *********************************/
/* Always Block */ 
always @(posedge CLK or negedge RST)
     begin
	     if(!RST)
	         begin			 
			     COUNT <= 3'b000 ; 	
			 end
	     else if (EN)
		     begin
	             COUNT <= COUNT + 3'b001 ;
	         end
	     else
		     begin
			     COUNT <= 3'b000 ; 	
			 end 
	 end

/****************************  Module End  ****************************/
endmodule

Shift_Register.v
/*************************************************************************/
/****        Author         :   Eslam Hussein                         ****/
/****        Module         :   Shift Register                        ****/
/****        Project Name   :   UART Transmitter                      ****/
/****        Date           :   1 August 2021                         ****/
/****        Version        :   V.01                                  ****/
/*************************************************************************/


/************************ Module Definition  *****************************/ 
module  Shift_Register  

/************************ Module Interface   *****************************/
     (
		 input  wire  [7:0]DATA_IN ,
         input  wire  CLK ,
		 input  wire  RST ,
		 input  wire  Load ,
		 input  wire  SHIFT  ,
		 output wire   DATA_OUT 
     );
	 
/************************  Module Body   *********************************/
/* Signal Declaration */ 
reg [7:0] date ; 
/* Always Block */ 
always @(posedge CLK or negedge RST)
     begin
	     if(!RST)
	         begin			 
			     date <= 8'b00000000 ; 	
			 end
	     else if (Load)
		     begin
			     
	             date <= DATA_IN ;	       			 
	         end
	     else if (SHIFT)
		     begin
				 date <= date >> 1'b1 ;
			 end 
	     else 
		     begin
				 date <= date  ;
			 end 			 
	 end
/* Assign Statement */
assign DATA_OUT = date[0] ;

/****************************  Module End  ****************************/
endmodule

UART_TX.v
/*************************************************************************/
/****        Author         :   Eslam Hussein                         ****/
/****        Module         :   UART_TX                               ****/
/****        Project Name   :   UART Transmitter                      ****/
/****        Description    :   Top Module                            ****/
/****        Date           :   1 August 2021                         ****/
/****        Version        :   V.01                                  ****/
/*************************************************************************/


/************************ Module Definition  *****************************/ 
module  UART_TX  

/************************ Module Interface   *****************************/
     (
		 input  wire  [7:0]P_DATA,
         input  wire  CLK ,
		 input  wire  RST ,
		 input  wire  Data_Valid ,
		 output wire   busy , 		 
		 output wire   S_DATA
     );
	 
/************************  Module Body   *********************************/
wire shift_w ;
wire counter_en_w ;
wire load_w ;
wire out_data_w ;
wire out_parity_bit_w ;
wire [1:0] sel_w ;
wire [2:0] count_w ;

Shift_Register  Shift_Register_A
     (
		.DATA_IN     (P_DATA)   ,
        .CLK         (CLK)   ,
		.RST         (RST)   ,
		.Load        (load_w)   ,
		.SHIFT       (shift_w)   ,
		.DATA_OUT    (out_data_w)
     );
Counter  Counter_A
     (
         .CLK     (CLK)  ,
		 .RST     (RST)  ,
		 .EN      (counter_en_w)  ,
		 .COUNT   (count_w) 
     );  
Parity_Calculator  Parity_Calculator_A
     (
	     .DATA_IN    (P_DATA) ,
         .CLK        (CLK) ,
	     .RST        (RST) ,
	     .Load       (load_w) ,
	     .Parity_Bit (out_parity_bit_w)
     );             
MUX  MUX_A
     (
        .I_0 (1'b1) ,
        .I_1 (1'b0) ,
        .I_2 (out_data_w) ,
        .I_3 (out_parity_bit_w) ,
		.SEL (sel_w) ,
		.OUT (S_DATA)
     );      
Control_Unit    Control_Unit_A
     (
		 .COUNT       (count_w) ,
         .CLK         (CLK) ,
		 .RST         (RST) ,
		 .Data_Valid  (Data_Valid) ,
		 .SHIFT       (shift_w) ,
		 .SEL         (sel_w) ,
		 .COUNT_EN    (counter_en_w) , 
		 .busy        (busy) , 		 
		 .Load        (load_w) 
     );
	 			 
/****************************  Module End  ****************************/
endmodule

UART_TX_TB.v
/*************************************************************************/
/****        Author         :   Eslam Hussein                         ****/
/****        Module         :   UART_TX_TB                            ****/
/****        Project Name   :   UART Transmitter                      ****/
/****        Description    :   Test Bench                            ****/
/****        Date           :   5 August 2021                         ****/
/****        Version        :   V.01                                  ****/
/*************************************************************************/

`timescale 1ns/1ps
/************************ Module Definition  *****************************/ 
module  UART_TX_TB  

/************************ Module Interface   *****************************/
     (
     );
	 
/**********************        Parameters          ***********************/
localparam CLK_PERIOD = 5 ;
localparam Test_Cases = 5 ;
/**********************      Loop Variable    ****************************/
integer                       Test_Case ;
/**********************       Memories        ****************************/
reg [10:0] Test_Patterns [Test_Cases-1:0] ;
reg [10:0] Expec_Outputs [Test_Cases-1:0] ;
/**********************  Signals  Declaration ****************************/
reg [7:0] P_DATA_TB;
reg CLK_TB ;
reg RST_TB ;
reg Data_Valid_TB ;
wire Busy_TB ; 		
wire S_DATA_TB ;

/*************************** Initial Block *******************************/
initial
     begin
	     $dumpfile("UART_TX_TB.vcd");
	     $dumpvars;
		 $readmemb("Patterns_b.txt", Test_Patterns);
         $readmemb("Expected_Outputs.txt", Expec_Outputs);
	     Initialize();
		 Restart();	
         for ( Test_Case = 0; Test_Case < Test_Cases ; Test_Case = Test_Case + 1 )
             begin
                 Creat_Test_Pattern(Test_Patterns[Test_Case]) ;                       
                 Check_Out_Response(Expec_Outputs[Test_Case],Test_Case) ;           
             end
		 #(10*CLK_PERIOD)
	     $finish; 
	 end
/************************ Initialization *********************************/
task Initialize;
     begin
	     CLK_TB = 1'b0 ; 
		 RST_TB = 2'b1 ;
		 Data_Valid_TB = 1'b0 ;
	 end
endtask
/************************ Restart Task ***********************************/
task Restart ;
     begin
          RST_TB = 1'b1 ; 
          #0.01
          RST_TB = 1'b0 ;
          #0.01
          RST_TB = 1'b1 ; 
     end
endtask
/************************ create Test Pattern Task ***********************/
task Creat_Test_Pattern ;
input  [7:0]data_in ;
     begin
	     P_DATA_TB = data_in ;
		 Data_Valid_TB = 1'b1 ;		 
		 Restart();
	 end
endtask
/************************ check Response Task ****************************/
task Check_Out_Response ;
input reg [10:0]Expected_Output ;
input integer  Operation_Number ; 
integer i;
reg [10:0]Generatrd_Output ;
     begin
         @( posedge Busy_TB )
		 Data_Valid_TB = 1'b0 ;
		 for(i=0; i<11; i=i+1)
		  begin
		  	 #CLK_PERIOD 
		 	 Generatrd_Output[i] = S_DATA_TB ;

          end				 
         if(Generatrd_Output == Expected_Output) 
              begin
                  $display("  Test Case %d Is  Succeeded",Operation_Number);
              end
          else
              begin
                  $display("  Test Case %d Is  Failed"  , Operation_Number);
	          end
	 end
endtask

/************************* Clock Generator *******************************/
always 
     begin
	     #(2.5) 
	     CLK_TB = ~CLK_TB ;
	 end
/****************** Unit Under Test Instantion ***************************/	 
UART_TX  UUT 
     (
		 .P_DATA(P_DATA_TB),
         .CLK (CLK_TB),
		 .RST (RST_TB),
		 .Data_Valid (Data_Valid_TB),
		 .busy (Busy_TB), 		 
		 .S_DATA(S_DATA_TB)
     );	  	 
/****************************  Module End  *******************************/
endmodule

UART_TX_TB.vcd
$date
	Sun Aug 08 04:15:49 2021
$end
$version
	ModelSim Version 10.1d
$end
$timescale
	1ps
$end
$scope module UART_TX_TB $end
$var parameter 32 ! CLK_PERIOD $end
$var parameter 32 " Test_Cases $end
$var integer 32 # Test_Case $end
$var reg 8 $ P_DATA_TB [7:0] $end
$var reg 1 % CLK_TB $end
$var reg 1 & RST_TB $end
$var reg 1 ' Data_Valid_TB $end
$var wire 1 ( Busy_TB $end
$var wire 1 ) S_DATA_TB $end
$scope task Initialize $end
$upscope $end
$scope task Restart $end
$upscope $end
$scope task Creat_Test_Pattern $end
$var reg 8 * data_in [7:0] $end
$upscope $end
$scope task Check_Out_Response $end
$var reg 11 + Expected_Output [10:0] $end
$var integer 32 , Operation_Number $end
$var integer 32 - i $end
$var reg 11 . Generatrd_Output [10:0] $end
$upscope $end
$scope module UUT $end
$var wire 1 / P_DATA [7] $end
$var wire 1 0 P_DATA [6] $end
$var wire 1 1 P_DATA [5] $end
$var wire 1 2 P_DATA [4] $end
$var wire 1 3 P_DATA [3] $end
$var wire 1 4 P_DATA [2] $end
$var wire 1 5 P_DATA [1] $end
$var wire 1 6 P_DATA [0] $end
$var wire 1 7 CLK $end
$var wire 1 8 RST $end
$var wire 1 9 Data_Valid $end
$var wire 1 ( busy $end
$var wire 1 ) S_DATA $end
$var wire 1 : shift_w $end
$var wire 1 ; counter_en_w $end
$var wire 1 < load_w $end
$var wire 1 = out_data_w $end
$var wire 1 > out_parity_bit_w $end
$var wire 1 ? sel_w [1] $end
$var wire 1 @ sel_w [0] $end
$var wire 1 A count_w [2] $end
$var wire 1 B count_w [1] $end
$var wire 1 C count_w [0] $end
$scope module Shift_Register_A $end
$var wire 1 / DATA_IN [7] $end
$var wire 1 0 DATA_IN [6] $end
$var wire 1 1 DATA_IN [5] $end
$var wire 1 2 DATA_IN [4] $end
$var wire 1 3 DATA_IN [3] $end
$var wire 1 4 DATA_IN [2] $end
$var wire 1 5 DATA_IN [1] $end
$var wire 1 6 DATA_IN [0] $end
$var wire 1 7 CLK $end
$var wire 1 8 RST $end
$var wire 1 < Load $end
$var wire 1 : SHIFT $end
$var wire 1 = DATA_OUT $end
$var reg 8 D date [7:0] $end
$upscope $end
$scope module Counter_A $end
$var wire 1 7 CLK $end
$var wire 1 8 RST $end
$var wire 1 ; EN $end
$var reg 3 E COUNT [2:0] $end
$upscope $end
$scope module Parity_Calculator_A $end
$var wire 1 / DATA_IN [7] $end
$var wire 1 0 DATA_IN [6] $end
$var wire 1 1 DATA_IN [5] $end
$var wire 1 2 DATA_IN [4] $end
$var wire 1 3 DATA_IN [3] $end
$var wire 1 4 DATA_IN [2] $end
$var wire 1 5 DATA_IN [1] $end
$var wire 1 6 DATA_IN [0] $end
$var wire 1 7 CLK $end
$var wire 1 8 RST $end
$var wire 1 < Load $end
$var wire 1 > Parity_Bit $end
$var reg 8 F data [7:0] $end
$upscope $end
$scope module MUX_A $end
$var wire 1 G I_0 $end
$var wire 1 H I_1 $end
$var wire 1 = I_2 $end
$var wire 1 > I_3 $end
$var wire 1 ? SEL [1] $end
$var wire 1 @ SEL [0] $end
$var reg 1 I OUT $end
$upscope $end
$scope module Control_Unit_A $end
$var parameter 3 J IDLE $end
$var parameter 3 K START $end
$var parameter 3 L D_SH $end
$var parameter 3 M INS_PAR $end
$var parameter 3 N STOP $end
$var wire 1 A COUNT [2] $end
$var wire 1 B COUNT [1] $end
$var wire 1 C COUNT [0] $end
$var wire 1 7 CLK $end
$var wire 1 8 RST $end
$var wire 1 9 Data_Valid $end
$var reg 1 O SHIFT $end
$var reg 2 P SEL [1:0] $end
$var reg 1 Q COUNT_EN $end
$var reg 1 R busy $end
$var reg 1 S Load $end
$var reg 3 T Current_State [2:0] $end
$var reg 3 U Next_State [2:0] $end
$upscope $end
$upscope $end
$upscope $end
$enddefinitions $end
#0
$dumpvars
bx $
0%
1&
0'
bx *
bx +
bx .
bx D
bx E
bx F
xI
xO
bx P
xQ
xR
xS
bx T
b0 U
b101 !
b101 "
b0 J
b1 K
b11 L
b111 M
b110 N
bx #
bx ,
bx -
x(
x)
x:
x;
x<
x=
x>
x@
x?
xC
xB
xA
09
18
07
x6
x5
x4
x3
x2
x1
x0
x/
0H
1G
$end
#10
0&
08
b0 D
b0 E
b0 F
b0 T
0=
0C
0B
0A
0>
0O
b0 P
0Q
0R
0S
0:
0;
0<
0@
0?
0(
1I
1)
#20
1&
b0 #
b10110011 *
b10110011 $
1'
16
15
04
03
12
11
00
1/
18
19
b1 U
#30
0&
08
#40
1&
b11101100110 +
b0 ,
18
#2500
1%
17
b1 T
1R
1S
b1 P
b11 U
1<
1(
1@
0I
0'
b0 -
0)
09
#5000
0%
07
#7500
bx0 .
b1 -
1%
17
b10110011 D
b10110011 F
b11 T
1=
1>
b0 P
0R
0S
1R
1Q
b10 P
1O
0<
1;
1:
0@
1?
1I
1)
#10000
0%
07
#12500
bx10 .
b10 -
1%
17
b1011001 D
b1 E
1C
#15000
0%
07
#17500
bx110 .
b11 -
1%
17
b101100 D
b10 E
0=
0C
1B
0I
0)
#20000
0%
07
#22500
bx0110 .
b100 -
1%
17
b10110 D
b11 E
1C
#25000
0%
07
#27500
bx00110 .
b101 -
1%
17
b1011 D
b100 E
1=
0C
0B
1A
1I
1)
#30000
0%
07
#32500
bx100110 .
b110 -
1%
17
b101 D
b101 E
1C
#35000
0%
07
#37500
bx1100110 .
b111 -
1%
17
b10 D
b110 E
0=
0C
1B
0I
0)
#40000
0%
07
#42500
bx01100110 .
b1000 -
1%
17
b1 D
b111 E
1=
1C
b111 U
1I
1)
#45000
0%
07
#47500
bx101100110 .
b1001 -
1%
17
b0 D
b0 E
b111 T
0=
0C
0B
0A
0I
0O
b0 P
0Q
0R
1R
b11 P
b110 U
0)
0:
0;
1@
1I
1)
#50000
0%
07
#52500
bx1101100110 .
b1010 -
1%
17
b110 T
b0 P
0R
1R
b0 U
0@
0?
#55000
0%
07
#57500
b11101100110 .
b1011 -
b1 #
b11110000 *
b11110000 $
1'
1%
06
05
10
19
17
b0 T
0R
b1 U
0(
#57510
0&
08
b0 F
0>
#57520
1&
b10111100000 +
b1 ,
18
#60000
0%
07
#62500
1%
17
b1 T
1R
1S
b1 P
b11 U
1<
1(
1@
0I
0'
b0 -
0)
09
#65000
0%
07
#67500
b1 -
1%
17
b11110000 D
b11110000 F
b11 T
b0 P
0R
0S
1R
1Q
b10 P
1O
0<
1;
1:
0@
1?
#70000
0%
07
#72500
b11101100100 .
b10 -
1%
17
b1111000 D
b1 E
1C
#75000
0%
07
#77500
b11101100000 .
b11 -
1%
17
b111100 D
b10 E
0C
1B
#80000
0%
07
#82500
b100 -
1%
17
b11110 D
b11 E
1C
#85000
0%
07
#87500
b101 -
1%
17
b1111 D
b100 E
1=
0C
0B
1A
1I
1)
#90000
0%
07
#92500
b110 -
1%
17
b111 D
b101 E
1C
#95000
0%
07
#97500
b111 -
1%
17
b11 D
b110 E
0C
1B
#100000
0%
07
#102500
b11111100000 .
b1000 -
1%
17
b1 D
b111 E
1C
b111 U
#105000
0%
07
#107500
b1001 -
1%
17
b0 D
b0 E
b111 T
0=
0C
0B
0A
0I
0O
b0 P
0Q
0R
1R
b11 P
b110 U
0)
0:
0;
1@
#110000
0%
07
#112500
b10111100000 .
b1010 -
1%
17
b110 T
b0 P
0R
1R
b0 U
0@
0?
1I
1)
#115000
0%
07
#117500
b1011 -
b10 #
b10101010 *
b10101010 $
1'
1%
15
13
02
00
19
17
b0 T
0R
b1 U
0(
#117510
0&
08
b0 F
#117520
1&
b10101010100 +
b10 ,
18
#120000
0%
07
#122500
1%
17
b1 T
1R
1S
b1 P
b11 U
1<
1(
1@
0I
0'
b0 -
0)
09
#125000
0%
07
#127500
b1 -
1%
17
b10101010 D
b10101010 F
b11 T
b0 P
0R
0S
1R
1Q
b10 P
1O
0<
1;
1:
0@
1?
#130000
0%
07
#132500
b10 -
1%
17
b1010101 D
b1 E
1=
1C
1I
1)
#135000
0%
07
#137500
b10111100100 .
b11 -
1%
17
b101010 D
b10 E
0=
0C
1B
0I
0)
#140000
0%
07
#142500
b100 -
1%
17
b10101 D
b11 E
1=
1C
1I
1)
#145000
0%
07
#147500
b10111110100 .
b101 -
1%
17
b1010 D
b100 E
0=
0C
0B
1A
0I
0)
#150000
0%
07
#152500
b10111010100 .
b110 -
1%
17
b101 D
b101 E
1=
1C
1I
1)
#155000
0%
07
#157500
b111 -
1%
17
b10 D
b110 E
0=
0C
1B
0I
0)
#160000
0%
07
#162500
b10101010100 .
b1000 -
1%
17
b1 D
b111 E
1=
1C
b111 U
1I
1)
#165000
0%
07
#167500
b1001 -
1%
17
b0 D
b0 E
b111 T
0=
0C
0B
0A
0I
0O
b0 P
0Q
0R
1R
b11 P
b110 U
0)
0:
0;
1@
#170000
0%
07
#172500
b1010 -
1%
17
b110 T
b0 P
0R
1R
b0 U
0@
0?
1I
1)
#175000
0%
07
#177500
b1011 -
b11 #
b11001100 *
b11001100 $
1'
1%
05
14
01
10
19
17
b0 T
0R
b1 U
0(
#177510
0&
08
b0 F
#177520
1&
b10110011000 +
b11 ,
18
#180000
0%
07
#182500
1%
17
b1 T
1R
1S
b1 P
b11 U
1<
1(
1@
0I
0'
b0 -
0)
09
#185000
0%
07
#187500
b1 -
1%
17
b11001100 D
b11001100 F
b11 T
b0 P
0R
0S
1R
1Q
b10 P
1O
0<
1;
1:
0@
1?
#190000
0%
07
#192500
b10 -
1%
17
b1100110 D
b1 E
1C
#195000
0%
07
#197500
b10101010000 .
b11 -
1%
17
b110011 D
b10 E
1=
0C
1B
1I
1)
#200000
0%
07
#202500
b10101011000 .
b100 -
1%
17
b11001 D
b11 E
1C
#205000
0%
07
#207500
b101 -
1%
17
b1100 D
b100 E
0=
0C
0B
1A
0I
0)
#210000
0%
07
#212500
b110 -
1%
17
b110 D
b101 E
1C
#215000
0%
07
#217500
b10100011000 .
b111 -
1%
17
b11 D
b110 E
1=
0C
1B
1I
1)
#220000
0%
07
#222500
b10110011000 .
b1000 -
1%
17
b1 D
b111 E
1C
b111 U
#225000
0%
07
#227500
b1001 -
1%
17
b0 D
b0 E
b111 T
0=
0C
0B
0A
0I
0O
b0 P
0Q
0R
1R
b11 P
b110 U
0)
0:
0;
1@
#230000
0%
07
#232500
b1010 -
1%
17
b110 T
b0 P
0R
1R
b0 U
0@
0?
1I
1)
#235000
0%
07
#237500
b1011 -
b100 #
b10101111 *
b10101111 $
1'
1%
16
15
11
00
19
17
b0 T
0R
b1 U
0(
#237510
0&
08
b0 F
#237520
1&
b10101011110 +
b100 ,
18
#240000
0%
07
#242500
1%
17
b1 T
1R
1S
b1 P
b11 U
1<
1(
1@
0I
0'
b0 -
0)
09
#245000
0%
07
#247500
b1 -
1%
17
b10101111 D
b10101111 F
b11 T
1=
b0 P
0R
0S
1R
1Q
b10 P
1O
0<
1;
1:
0@
1?
1I
1)
#250000
0%
07
#252500
b10110011010 .
b10 -
1%
17
b1010111 D
b1 E
1C
#255000
0%
07
#257500
b10110011110 .
b11 -
1%
17
b101011 D
b10 E
0C
1B
#260000
0%
07
#262500
b100 -
1%
17
b10101 D
b11 E
1C
#265000
0%
07
#267500
b101 -
1%
17
b1010 D
b100 E
0=
0C
0B
1A
0I
0)
#270000
0%
07
#272500
b110 -
1%
17
b101 D
b101 E
1=
1C
1I
1)
#275000
0%
07
#277500
b10111011110 .
b111 -
1%
17
b10 D
b110 E
0=
0C
1B
0I
0)
#280000
0%
07
#282500
b10101011110 .
b1000 -
1%
17
b1 D
b111 E
1=
1C
b111 U
1I
1)
#285000
0%
07
#287500
b1001 -
1%
17
b0 D
b0 E
b111 T
0=
0C
0B
0A
0I
0O
b0 P
0Q
0R
1R
b11 P
b110 U
0)
0:
0;
1@
#290000
0%
07
#292500
b1010 -
1%
17
b110 T
b0 P
0R
1R
b0 U
0@
0?
1I
1)
#295000
0%
07
#297500
b1011 -
b101 #
1%
17
b0 T
0R
0(
